webp3/__init__.py
webp3/__main__.py
webp3/app.py
webp3/conf.py
webp3/exceptions.py
webp3/main_wsgi.py
webp3/pathutils.py
webp3/requestutils.py
webp3/webp3.wsgi
webp3/static/COPYING.WTFPL
webp3/static/base.tpl
webp3/static/favicon.png
webp3/static/player.js
webp3/static/style.css
webp3-1.3.1.data/data/share/webp3/apache/install-webp3.rst
webp3-1.3.1.data/data/share/webp3/apache/webp3.conf
webp3-1.3.1.dist-info/METADATA
webp3-1.3.1.dist-info/WHEEL
webp3-1.3.1.dist-info/entry_points.txt
webp3-1.3.1.dist-info/licenses/COPYING.WTFPL
webp3-1.3.1.dist-info/RECORD
