Metadata-Version: 2.4
Name: webp3
Version: 1.3.1
Summary: Music player web app
Project-URL: Homepage, https://gitlab.com/hydrargyrum/webp3
Author-email: Hg <dev@indigo.re>
License-Expression: WTFPL
License-File: COPYING.WTFPL
Keywords: audio,html5,music,player,server,web
Classifier: Development Status :: 4 - Beta
Classifier: Environment :: Web Environment
Classifier: Framework :: Bottle
Classifier: Intended Audience :: End Users/Desktop
Classifier: License :: CC0 1.0 Universal (CC0 1.0) Public Domain Dedication
Classifier: License :: Public Domain
Classifier: Programming Language :: Python :: 3
Classifier: Programming Language :: Python :: 3.8
Classifier: Programming Language :: Python :: 3.9
Classifier: Programming Language :: Python :: 3.10
Classifier: Programming Language :: Python :: 3.11
Classifier: Programming Language :: Python :: 3.12
Classifier: Programming Language :: Python :: 3.13
Classifier: Topic :: Internet :: WWW/HTTP :: WSGI :: Application
Classifier: Topic :: Multimedia :: Sound/Audio :: Players
Requires-Python: >=3
Requires-Dist: bottle
Requires-Dist: mako>1.0
